{
  "book_name": "Nehemiah",
  "chapter": 12,
  "verses": [
    {
      "book_name": "Nehemiah",
      "chapter": 12,
      "verse": 1,
      "text": "Now these <i>are</i> the priests and the Levites that went up with Zerubbabel the son of Shealtiel, and Jeshua: Seraiah, Jeremiah, Ezra,",
      "header": "",
      "footer": ""
    },
    {
      "book_name": "Nehemiah",
      "chapter": 12,
      "verse": 2,
      "text": "Amariah, Malluch, Hattush,",
      "header": "",
      "footer": ""
    },
    {
      "book_name": "Nehemiah",
      "chapter": 12,
      "verse": 3,
      "text": "Shechaniah, Rehum, Meremoth,",
      "header": "",
      "footer": ""
    },
    {
      "book_name": "Nehemiah",
      "chapter": 12,
      "verse": 4,
      "text": "Iddo, Ginnetho, Abijah,",
      "header": "",
      "footer": ""
    },
    {
      "book_name": "Nehemiah",
      "chapter": 12,
      "verse": 5,
      "text": "Miamin, Maadiah, Bilgah,",
      "header": "",
      "footer": ""
    },
    {
      "book_name": "Nehemiah",
      "chapter": 12,
      "verse": 6,
      "text": "Shemaiah, and Joiarib, Jedaiah,",
      "header": "",
      "footer": ""
    },
    {
      "book_name": "Nehemiah",
      "chapter": 12,
      "verse": 7,
      "text": "Sallu, Amok, Hilkiah, Jedaiah. These <i>were</i> the chief of the priests and of their brethren in the days of Jeshua.",
      "header": "",
      "footer": ""
    },
    {
      "book_name": "Nehemiah",
      "chapter": 12,
      "verse": 8,
      "text": "Moreover the Levites: Jeshua, Binnui, Kadmiel, Sherebiah, Judah, <i>and</i> Mattaniah, <i>which was</i> over the thanksgiving, he and his brethren.",
      "header": "",
      "footer": ""
    },
    {
      "book_name": "Nehemiah",
      "chapter": 12,
      "verse": 9,
      "text": "Also Bakbukiah and Unni, their brethren, <i>were</i> over against them in the watches.",
      "header": "",
      "footer": ""
    },
    {
      "book_name": "Nehemiah",
      "chapter": 12,
      "verse": 10,
      "text": "¶ And Jeshua begat Joiakim, Joiakim also begat Eliashib, and Eliashib begat Joiada,",
      "header": "",
      "footer": ""
    },
    {
      "book_name": "Nehemiah",
      "chapter": 12,
      "verse": 11,
      "text": "And Joiada begat Jonathan, and Jonathan begat Jaddua.",
      "header": "",
      "footer": ""
    },
    {
      "book_name": "Nehemiah",
      "chapter": 12,
      "verse": 12,
      "text": "And in the days of Joiakim were priests, the chief of the fathers: of Seraiah, Meraiah; of Jeremiah, Hananiah;",
      "header": "",
      "footer": ""
    },
    {
      "book_name": "Nehemiah",
      "chapter": 12,
      "verse": 13,
      "text": "Of Ezra, Meshullam; of Amariah, Jehohanan;",
      "header": "",
      "footer": ""
    },
    {
      "book_name": "Nehemiah",
      "chapter": 12,
      "verse": 14,
      "text": "Of Melicu, Jonathan; of Shebaniah, Joseph;",
      "header": "",
      "footer": ""
    },
    {
      "book_name": "Nehemiah",
      "chapter": 12,
      "verse": 15,
      "text": "Of Harim, Adna; of Meraioth, Helkai;",
      "header": "",
      "footer": ""
    },
    {
      "book_name": "Nehemiah",
      "chapter": 12,
      "verse": 16,
      "text": "Of Iddo, Zechariah; of Ginnethon, Meshullam;",
      "header": "",
      "footer": ""
    },
    {
      "book_name": "Nehemiah",
      "chapter": 12,
      "verse": 17,
      "text": "Of Abijah, Zichri; of Miniamin, of Moadiah, Piltai;",
      "header": "",
      "footer": ""
    },
    {
      "book_name": "Nehemiah",
      "chapter": 12,
      "verse": 18,
      "text": "Of Bilgah, Shammua; of Shemaiah, Jehonathan;",
      "header": "",
      "footer": ""
    },
    {
      "book_name": "Nehemiah",
      "chapter": 12,
      "verse": 19,
      "text": "And of Joiarib, Mattenai; of Jedaiah, Uzzi;",
      "header": "",
      "footer": ""
    },
    {
      "book_name": "Nehemiah",
      "chapter": 12,
      "verse": 20,
      "text": "Of Sallai, Kallai; of Amok, Eber;",
      "header": "",
      "footer": ""
    },
    {
      "book_name": "Nehemiah",
      "chapter": 12,
      "verse": 21,
      "text": "Of Hilkiah, Hashabiah; of Jedaiah, Nethaneel.",
      "header": "",
      "footer": ""
    },
    {
      "book_name": "Nehemiah",
      "chapter": 12,
      "verse": 22,
      "text": "¶ The Levites in the days of Eliashib, Joiada, and Johanan, and Jaddua, <i>were</i> recorded chief of the fathers: also the priests, to the reign of Darius the Persian.",
      "header": "",
      "footer": ""
    },
    {
      "book_name": "Nehemiah",
      "chapter": 12,
      "verse": 23,
      "text": "The sons of Levi, the chief of the fathers, <i>were</i> written in the book of the chronicles, even until the days of Johanan the son of Eliashib.",
      "header": "",
      "footer": ""
    },
    {
      "book_name": "Nehemiah",
      "chapter": 12,
      "verse": 24,
      "text": "And the chief of the Levites: Hashabiah, Sherebiah, and Jeshua the son of Kadmiel, with their brethren over against them, to praise <i>and</i> to give thanks, according to the commandment of David the man of God, ward over against ward.",
      "header": "",
      "footer": ""
    },
    {
      "book_name": "Nehemiah",
      "chapter": 12,
      "verse": 25,
      "text": "Mattaniah, and Bakbukiah, Obadiah, Meshullam, Talmon, Akkub, <i>were</i> porters keeping the ward at the thresholds of the gates.",
      "header": "",
      "footer": ""
    },
    {
      "book_name": "Nehemiah",
      "chapter": 12,
      "verse": 26,
      "text": "These <i>were</i> in the days of Joiakim the son of Jeshua, the son of Jozadak, and in the days of Nehemiah the governor, and of Ezra the priest, the scribe.",
      "header": "",
      "footer": ""
    },
    {
      "book_name": "Nehemiah",
      "chapter": 12,
      "verse": 27,
      "text": "¶ And at the dedication of the wall of Jerusalem they sought the Levites out of all their places, to bring them to Jerusalem, to keep the dedication with gladness, both with thanksgivings, and with singing, <i>with</i> cymbals, psalteries, and with harps.",
      "header": "",
      "footer": ""
    },
    {
      "book_name": "Nehemiah",
      "chapter": 12,
      "verse": 28,
      "text": "And the sons of the singers gathered themselves together, both out of the plain country round about Jerusalem, and from the villages of Netophathi;",
      "header": "",
      "footer": ""
    },
    {
      "book_name": "Nehemiah",
      "chapter": 12,
      "verse": 29,
      "text": "Also from the house of Gilgal, and out of the fields of Geba and Azmaveth: for the singers had builded them villages round about Jerusalem.",
      "header": "",
      "footer": ""
    },
    {
      "book_name": "Nehemiah",
      "chapter": 12,
      "verse": 30,
      "text": "And the priests and the Levites purified themselves, and purified the people, and the gates, and the wall.",
      "header": "",
      "footer": ""
    },
    {
      "book_name": "Nehemiah",
      "chapter": 12,
      "verse": 31,
      "text": "Then I brought up the princes of Judah upon the wall, and appointed two great <i>companies of them that gave</i> thanks, <i>whereof one</i> went on the right hand upon the wall toward the dung gate:",
      "header": "",
      "footer": ""
    },
    {
      "book_name": "Nehemiah",
      "chapter": 12,
      "verse": 32,
      "text": "And after them went Hoshaiah, and half of the princes of Judah,",
      "header": "",
      "footer": ""
    },
    {
      "book_name": "Nehemiah",
      "chapter": 12,
      "verse": 33,
      "text": "And Azariah, Ezra, and Meshullam,",
      "header": "",
      "footer": ""
    },
    {
      "book_name": "Nehemiah",
      "chapter": 12,
      "verse": 34,
      "text": "Judah, and Benjamin, and Shemaiah, and Jeremiah,",
      "header": "",
      "footer": ""
    },
    {
      "book_name": "Nehemiah",
      "chapter": 12,
      "verse": 35,
      "text": "And <i>certain</i> of the priests' sons with trumpets; <i>namely,</i> Zechariah the son of Jonathan, the son of Shemaiah, the son of Mattaniah, the son of Michaiah, the son of Zaccur, the son of Asaph:",
      "header": "",
      "footer": ""
    },
    {
      "book_name": "Nehemiah",
      "chapter": 12,
      "verse": 36,
      "text": "And his brethren, Shemaiah, and Azarael, Milalai, Gilalai, Maai, Nethaneel, and Judah, Hanani, with the musical instruments of David the man of God, and Ezra the scribe before them.",
      "header": "",
      "footer": ""
    },
    {
      "book_name": "Nehemiah",
      "chapter": 12,
      "verse": 37,
      "text": "And at the fountain gate, which was over against them, they went up by the stairs of the city of David, at the going up of the wall, above the house of David, even unto the water gate eastward.",
      "header": "",
      "footer": ""
    },
    {
      "book_name": "Nehemiah",
      "chapter": 12,
      "verse": 38,
      "text": "And the other <i>company of them that gave</i> thanks went over against <i>them,</i> and I after them, and the half of the people upon the wall, from beyond the tower of the furnaces even unto the broad wall;",
      "header": "",
      "footer": ""
    },
    {
      "book_name": "Nehemiah",
      "chapter": 12,
      "verse": 39,
      "text": "And from above the gate of Ephraim, and above the old gate, and above the fish gate, and the tower of Hananeel, and the tower of Meah, even unto the sheep gate: and they stood still in the prison gate.",
      "header": "",
      "footer": ""
    },
    {
      "book_name": "Nehemiah",
      "chapter": 12,
      "verse": 40,
      "text": "So stood the two <i>companies of them that gave</i> thanks in the house of God, and I, and the half of the rulers with me:",
      "header": "",
      "footer": ""
    },
    {
      "book_name": "Nehemiah",
      "chapter": 12,
      "verse": 41,
      "text": "And the priests; Eliakim, Maaseiah, Miniamin, Michaiah, Elioenai, Zechariah, <i>and</i> Hananiah, with trumpets;",
      "header": "",
      "footer": ""
    },
    {
      "book_name": "Nehemiah",
      "chapter": 12,
      "verse": 42,
      "text": "And Maaseiah, and Shemaiah, and Eleazar, and Uzzi, and Jehohanan, and Malchijah, and Elam, and Ezer. And the singers sang loud, with Jezrahiah <i>their</i> overseer.",
      "header": "",
      "footer": ""
    },
    {
      "book_name": "Nehemiah",
      "chapter": 12,
      "verse": 43,
      "text": "Also that day they offered great sacrifices, and rejoiced: for God had made them rejoice with great joy: the wives also and the children rejoiced: so that the joy of Jerusalem was heard even afar off.",
      "header": "",
      "footer": ""
    },
    {
      "book_name": "Nehemiah",
      "chapter": 12,
      "verse": 44,
      "text": "¶ And at that time were some appointed over the chambers for the treasures, for the offerings, for the firstfruits, and for the tithes, to gather into them out of the fields of the cities the portions of the law for the priests and Levites: for Judah rejoiced for the priests and for the Levites that waited.",
      "header": "",
      "footer": ""
    },
    {
      "book_name": "Nehemiah",
      "chapter": 12,
      "verse": 45,
      "text": "And both the singers and the porters kept the ward of their God, and the ward of the purification, according to the commandment of David, <i>and</i> of Solomon his son.",
      "header": "",
      "footer": ""
    },
    {
      "book_name": "Nehemiah",
      "chapter": 12,
      "verse": 46,
      "text": "For in the days of David and Asaph of old <i>there were</i> chief of the singers, and songs of praise and thanksgiving unto God.",
      "header": "",
      "footer": ""
    },
    {
      "book_name": "Nehemiah",
      "chapter": 12,
      "verse": 47,
      "text": "And all Israel in the days of Zerubbabel, and in the days of Nehemiah, gave the portions of the singers and the porters, every day his portion: and they sanctified <i>holy things</i> unto the Levites; and the Levites sanctified <i>them</i> unto the children of Aaron.",
      "header": "",
      "footer": ""
    }
  ]
}