{
  "book_name": "Psalms",
  "chapter": 110,
  "verses": [
    {
      "book_name": "Psalms",
      "chapter": 110,
      "verse": 1,
      "text": "The LORD said unto my Lord, Sit thou at my right hand, until I make thine enemies thy footstool.",
      "header": "¶ A Psalm of David.",
      "footer": ""
    },
    {
      "book_name": "Psalms",
      "chapter": 110,
      "verse": 2,
      "text": "The LORD shall send the rod of thy strength out of Zion: rule thou in the midst of thine enemies.",
      "header": "",
      "footer": ""
    },
    {
      "book_name": "Psalms",
      "chapter": 110,
      "verse": 3,
      "text": "Thy people <i>shall be</i> willing in the day of thy power, in the beauties of holiness from the womb of the morning: thou hast the dew of thy youth.",
      "header": "",
      "footer": ""
    },
    {
      "book_name": "Psalms",
      "chapter": 110,
      "verse": 4,
      "text": "The LORD hath sworn, and will not repent, Thou <i>art</i> a priest for ever after the order of Melchizedek.",
      "header": "",
      "footer": ""
    },
    {
      "book_name": "Psalms",
      "chapter": 110,
      "verse": 5,
      "text": "The Lord at thy right hand shall strike through kings in the day of his wrath.",
      "header": "",
      "footer": ""
    },
    {
      "book_name": "Psalms",
      "chapter": 110,
      "verse": 6,
      "text": "He shall judge among the heathen, he shall fill <i>the places</i> with the dead bodies; he shall wound the heads over many countries.",
      "header": "",
      "footer": ""
    },
    {
      "book_name": "Psalms",
      "chapter": 110,
      "verse": 7,
      "text": "He shall drink of the brook in the way: therefore shall he lift up the head.",
      "header": "",
      "footer": ""
    }
  ]
}