{
  "book_name": "Psalms",
  "chapter": 134,
  "verses": [
    {
      "book_name": "Psalms",
      "chapter": 134,
      "verse": 1,
      "text": "Behold, bless ye the LORD, all <i>ye</i> servants of the LORD, which by night stand in the house of the LORD.",
      "header": "¶ A Song of degrees.",
      "footer": ""
    },
    {
      "book_name": "Psalms",
      "chapter": 134,
      "verse": 2,
      "text": "Lift up your hands <i>in</i> the sanctuary, and bless the LORD.",
      "header": "",
      "footer": ""
    },
    {
      "book_name": "Psalms",
      "chapter": 134,
      "verse": 3,
      "text": "The LORD that made heaven and earth bless thee out of Zion.",
      "header": "",
      "footer": ""
    }
  ]
}